<?xml version="1.0" encoding="utf-8"?><TransliterationCorpus CorpusFormat="Default" CorpusID="Default" CorpusSize="500" CorpusType="Tune" NameSource="Default" SourceLang="Default" TargetLang="Default"><Name ID="1"><SourceName>accra</SourceName><TargetName ID="1">ácra</TargetName></Name><Name ID="2"><SourceName>alajuela</SourceName><TargetName ID="1">alagiuêla</TargetName></Name><Name ID="3"><SourceName>alaungpaya</SourceName><TargetName ID="1">alaungbada</TargetName></Name><Name ID="4"><SourceName>allende</SourceName><TargetName ID="1">alienđê</TargetName></Name><Name ID="5"><SourceName>almaty</SourceName><TargetName ID="1">anmati</TargetName></Name><Name ID="6"><SourceName>amazon</SourceName><TargetName ID="1">amagiôn</TargetName></Name><Name ID="7"><SourceName>ambon</SourceName><TargetName ID="1">ambon</TargetName></Name><Name ID="8"><SourceName>amenophis</SourceName><TargetName ID="1">amênôphít</TargetName></Name><Name ID="9"><SourceName>anadolu</SourceName><TargetName ID="1">anađôlu</TargetName></Name><Name ID="10"><SourceName>anbani</SourceName><TargetName ID="1">anbani</TargetName></Name><Name ID="11"><SourceName>andersen</SourceName><TargetName ID="1">anđécxen</TargetName></Name><Name ID="12"><SourceName>andrianovich</SourceName><TargetName ID="1">anđờrianôvích</TargetName></Name><Name ID="13"><SourceName>angara</SourceName><TargetName ID="1">angara</TargetName></Name><Name ID="14"><SourceName>angel</SourceName><TargetName ID="1">engiô</TargetName></Name><Name ID="15"><SourceName>annibal</SourceName><TargetName ID="1">aniban</TargetName></Name><Name ID="16"><SourceName>aphrodite</SourceName><TargetName ID="1">aphờrôđít</TargetName></Name><Name ID="17"><SourceName>appell</SourceName><TargetName ID="1">aben</TargetName></Name><Name ID="18"><SourceName>arakan</SourceName><TargetName ID="1">aracan</TargetName></Name><Name ID="19"><SourceName>araks</SourceName><TargetName ID="1">arácxơ</TargetName></Name><Name ID="20"><SourceName>ardenne</SourceName><TargetName ID="1">ácđen</TargetName></Name><Name ID="21"><SourceName>arman</SourceName><TargetName ID="1">ácman</TargetName></Name><Name ID="22"><SourceName>asanga</SourceName><TargetName ID="1">asanga</TargetName></Name><Name ID="23"><SourceName>aseb</SourceName><TargetName ID="1">axép</TargetName></Name><Name ID="24"><SourceName>asplund</SourceName><TargetName ID="1">axơphờlun</TargetName></Name><Name ID="25"><SourceName>assyrie</SourceName><TargetName ID="1">asiri</TargetName></Name><Name ID="26"><SourceName>asuncion</SourceName><TargetName ID="1">axunxiôn</TargetName></Name><Name ID="27"><SourceName>at</SourceName><TargetName ID="1">át</TargetName></Name><Name ID="28"><SourceName>atacama</SourceName><TargetName ID="1">atacama</TargetName></Name><Name ID="29"><SourceName>atahualpa</SourceName><TargetName ID="1">atahuanba</TargetName></Name><Name ID="30"><SourceName>attica</SourceName><TargetName ID="1">áttica</TargetName></Name><Name ID="31"><SourceName>augustus</SourceName><TargetName ID="1">auguxờtút</TargetName></Name><Name ID="32"><SourceName>austerlitz</SourceName><TargetName ID="1">aoxờtéclít</TargetName></Name><Name ID="33"><SourceName>avignon</SourceName><TargetName ID="1">avinhông</TargetName></Name><Name ID="34"><SourceName>baargeld</SourceName><TargetName ID="1">bácghen</TargetName></Name><Name ID="35"><SourceName>bacchus</SourceName><TargetName ID="1">báccớt</TargetName></Name><Name ID="36"><SourceName>bachelard</SourceName><TargetName ID="1">basơla</TargetName></Name><Name ID="37"><SourceName>badminton</SourceName><TargetName ID="1">bátmintơn</TargetName></Name><Name ID="38"><SourceName>baharu</SourceName><TargetName ID="1">baharu</TargetName></Name><Name ID="39"><SourceName>bakunin</SourceName><TargetName ID="1">bacunin</TargetName></Name><Name ID="40"><SourceName>balabac</SourceName><TargetName ID="1">balabác</TargetName></Name><Name ID="41"><SourceName>balaton</SourceName><TargetName ID="1">balatơn</TargetName></Name><Name ID="42"><SourceName>balearic</SourceName><TargetName ID="1">balêari</TargetName></Name><Name ID="43"><SourceName>balzac</SourceName><TargetName ID="1">bangiắc</TargetName></Name><Name ID="44"><SourceName>bandama</SourceName><TargetName ID="1">băngđama</TargetName></Name><Name ID="45"><SourceName>bandung</SourceName><TargetName ID="1">banđưng</TargetName></Name><Name ID="46"><SourceName>bangweulu</SourceName><TargetName ID="1">bangguêulu</TargetName></Name><Name ID="47"><SourceName>barbados</SourceName><TargetName ID="1">bắcbađốt</TargetName></Name><Name ID="48"><SourceName>barber</SourceName><TargetName ID="1">bácbơ</TargetName></Name><Name ID="49"><SourceName>baroja</SourceName><TargetName ID="1">barôgia</TargetName></Name><Name ID="50"><SourceName>barthes</SourceName><TargetName ID="1">bátthơ</TargetName></Name><Name ID="51"><SourceName>bartolomeo</SourceName><TargetName ID="1">báctôlômêô</TargetName></Name><Name ID="52"><SourceName>basel</SourceName><TargetName ID="1">baseo</TargetName></Name><Name ID="53"><SourceName>bassac</SourceName><TargetName ID="1">bátxắc</TargetName></Name><Name ID="54"><SourceName>basse</SourceName><TargetName ID="1">basơ</TargetName></Name><Name ID="55"><SourceName>bawerk</SourceName><TargetName ID="1">bavéc</TargetName></Name><Name ID="56"><SourceName>bayard</SourceName><TargetName ID="1">bâyát</TargetName></Name><Name ID="57"><SourceName>beauchamp</SourceName><TargetName ID="1">biusam</TargetName></Name><Name ID="58"><SourceName>becquerel</SourceName><TargetName ID="1">bécquereo</TargetName></Name><Name ID="59"><SourceName>begichev</SourceName><TargetName ID="1">bêghichép</TargetName></Name><Name ID="60"><SourceName>bela</SourceName><TargetName ID="1">bela</TargetName></Name><Name ID="61"><SourceName>belyj</SourceName><TargetName ID="1">bêli</TargetName></Name><Name ID="62"><SourceName>berezina</SourceName><TargetName ID="1">bêrêgina</TargetName></Name><Name ID="63"><SourceName>bermuda</SourceName><TargetName ID="1">bécmuđa</TargetName></Name><Name ID="64"><SourceName>bernini</SourceName><TargetName ID="1">bécnini</TargetName></Name><Name ID="65"><SourceName>bernshtejn</SourceName><TargetName ID="1">bơnsờtêin</TargetName></Name><Name ID="66"><SourceName>bernstein</SourceName><TargetName ID="1">bơnsờtêin</TargetName></Name><Name ID="67"><SourceName>bessemer</SourceName><TargetName ID="1">bétsemmơ</TargetName></Name><Name ID="68"><SourceName>beti</SourceName><TargetName ID="1">bêti</TargetName></Name><Name ID="69"><SourceName>bezout</SourceName><TargetName ID="1">bêgiu</TargetName></Name><Name ID="70"><SourceName>bhavabhuti</SourceName><TargetName ID="1">bờhavabờhuti</TargetName></Name><Name ID="71"><SourceName>biarritz</SourceName><TargetName ID="1">biarít</TargetName></Name><Name ID="72"><SourceName>bilbao</SourceName><TargetName ID="1">binbao</TargetName></Name><Name ID="73"><SourceName>biot</SourceName><TargetName ID="1">biốt</TargetName></Name><Name ID="74"><SourceName>birmingham</SourceName><TargetName ID="1">bớtminhham</TargetName></Name><Name ID="75"><SourceName>blagoveshchensk</SourceName><TargetName ID="1">bờlagôvétsencơ</TargetName></Name><Name ID="76"><SourceName>blankenburg</SourceName><TargetName ID="1">bờlankenbớt</TargetName></Name><Name ID="77"><SourceName>blok</SourceName><TargetName ID="1">bờlốc</TargetName></Name><Name ID="78"><SourceName>boden</SourceName><TargetName ID="1">bôđen</TargetName></Name><Name ID="79"><SourceName>bodrum</SourceName><TargetName ID="1">bôđờrum</TargetName></Name><Name ID="80"><SourceName>bongor</SourceName><TargetName ID="1">bongô</TargetName></Name><Name ID="81"><SourceName>borel</SourceName><TargetName ID="1">bôren</TargetName></Name><Name ID="82"><SourceName>borisov</SourceName><TargetName ID="1">bôrixốp</TargetName></Name><Name ID="83"><SourceName>borodin</SourceName><TargetName ID="1">bôrôđin</TargetName></Name><Name ID="84"><SourceName>boroma</SourceName><TargetName ID="1">bôrôma</TargetName></Name><Name ID="85"><SourceName>bosphore</SourceName><TargetName ID="1">bốtpho</TargetName></Name><Name ID="86"><SourceName>boswash</SourceName><TargetName ID="1">bôsờquát</TargetName></Name><Name ID="87"><SourceName>botkin</SourceName><TargetName ID="1">bốtkin</TargetName></Name><Name ID="88"><SourceName>botnie</SourceName><TargetName ID="1">bốtni</TargetName></Name><Name ID="89"><SourceName>botticelli</SourceName><TargetName ID="1">bôtixeli</TargetName></Name><Name ID="90"><SourceName>bouar</SourceName><TargetName ID="1">bua</TargetName></Name><Name ID="91"><SourceName>boulez</SourceName><TargetName ID="1">bulêgiơ</TargetName></Name><Name ID="92"><SourceName>bourdelle</SourceName><TargetName ID="1">buốcđen</TargetName></Name><Name ID="93"><SourceName>boutros</SourceName><TargetName ID="1">butrốt</TargetName></Name><Name ID="94"><SourceName>bowen</SourceName><TargetName ID="1">bôquen</TargetName></Name><Name ID="95"><SourceName>braille</SourceName><TargetName ID="1">bờrai</TargetName></Name><Name ID="96"><SourceName>bran</SourceName><TargetName ID="1">bờranđô</TargetName></Name><Name ID="97"><SourceName>brazzaville</SourceName><TargetName ID="1">bờragiavin</TargetName></Name><Name ID="98"><SourceName>bremen</SourceName><TargetName ID="1">bờrêmen</TargetName></Name><Name ID="99"><SourceName>breuer</SourceName><TargetName ID="1">bờrơ</TargetName></Name><Name ID="100"><SourceName>bristol</SourceName><TargetName ID="1">bờrixờtơn</TargetName></Name><Name ID="101"><SourceName>britten</SourceName><TargetName ID="1">bờríttơn</TargetName></Name><Name ID="102"><SourceName>bromlej</SourceName><TargetName ID="1">bờrômlây</TargetName></Name><Name ID="103"><SourceName>bruegel</SourceName><TargetName ID="1">bờrughen</TargetName></Name><Name ID="104"><SourceName>brugge</SourceName><TargetName ID="1">bờruygơ</TargetName></Name><Name ID="105"><SourceName>buchanan</SourceName><TargetName ID="1">biucanơn</TargetName></Name><Name ID="106"><SourceName>buchenwald</SourceName><TargetName ID="1">bukhenvan</TargetName></Name><Name ID="107"><SourceName>buffalo</SourceName><TargetName ID="1">baphơlâu</TargetName></Name><Name ID="108"><SourceName>bunjakovskij</SourceName><TargetName ID="1">bungiakốpsờki</TargetName></Name><Name ID="109"><SourceName>burchett</SourceName><TargetName ID="1">bơchét</TargetName></Name><Name ID="110"><SourceName>burly</SourceName><TargetName ID="1">bơly</TargetName></Name><Name ID="111"><SourceName>butenandt</SourceName><TargetName ID="1">butơnan</TargetName></Name><Name ID="112"><SourceName>butiaba</SourceName><TargetName ID="1">butiaba</TargetName></Name><Name ID="113"><SourceName>cairo</SourceName><TargetName ID="1">cairô</TargetName></Name><Name ID="114"><SourceName>callao</SourceName><TargetName ID="1">calao</TargetName></Name><Name ID="115"><SourceName>caloocan</SourceName><TargetName ID="1">calôôcan</TargetName></Name><Name ID="116"><SourceName>camus</SourceName><TargetName ID="1">camút</TargetName></Name><Name ID="117"><SourceName>canberra</SourceName><TargetName ID="1">canbơrơ</TargetName></Name><Name ID="118"><SourceName>cannes</SourceName><TargetName ID="1">can</TargetName></Name><Name ID="119"><SourceName>caparra</SourceName><TargetName ID="1">cabara</TargetName></Name><Name ID="120"><SourceName>carlyle</SourceName><TargetName ID="1">calai</TargetName></Name><Name ID="121"><SourceName>carolingiens</SourceName><TargetName ID="1">carôlingien</TargetName></Name><Name ID="122"><SourceName>carpentier</SourceName><TargetName ID="1">cabenthaiơ</TargetName></Name><Name ID="123"><SourceName>cascade</SourceName><TargetName ID="1">caxờcát</TargetName></Name><Name ID="124"><SourceName>caselli</SourceName><TargetName ID="1">caxêli</TargetName></Name><Name ID="125"><SourceName>castries</SourceName><TargetName ID="1">cáttri</TargetName></Name><Name ID="126"><SourceName>catal</SourceName><TargetName ID="1">catan</TargetName></Name><Name ID="127"><SourceName>cataldi</SourceName><TargetName ID="1">catanđi</TargetName></Name><Name ID="128"><SourceName>chadwick</SourceName><TargetName ID="1">chađuých</TargetName></Name><Name ID="129"><SourceName>chakri</SourceName><TargetName ID="1">chắcri</TargetName></Name><Name ID="130"><SourceName>chandrasekhar</SourceName><TargetName ID="1">chanđờraxêca</TargetName></Name><Name ID="131"><SourceName>cheljuskin</SourceName><TargetName ID="1">chêliuxờkin</TargetName></Name><Name ID="132"><SourceName>chernyshevskij</SourceName><TargetName ID="1">chécnưsépxờki</TargetName></Name><Name ID="133"><SourceName>chindwin</SourceName><TargetName ID="1">chinđuin</TargetName></Name><Name ID="134"><SourceName>claudel</SourceName><TargetName ID="1">cờlôđen</TargetName></Name><Name ID="135"><SourceName>cockcroft</SourceName><TargetName ID="1">cốccờrốp</TargetName></Name><Name ID="136"><SourceName>colbert</SourceName><TargetName ID="1">cônbớt</TargetName></Name><Name ID="137"><SourceName>coleridge</SourceName><TargetName ID="1">câulơrít</TargetName></Name><Name ID="138"><SourceName>collin</SourceName><TargetName ID="1">côlin</TargetName></Name><Name ID="139"><SourceName>coloane</SourceName><TargetName ID="1">côlôan</TargetName></Name><Name ID="140"><SourceName>cologne</SourceName><TargetName ID="1">côlônhơ</TargetName></Name><Name ID="141"><SourceName>colophon</SourceName><TargetName ID="1">côlôphôn</TargetName></Name><Name ID="142"><SourceName>comino</SourceName><TargetName ID="1">côminô</TargetName></Name><Name ID="143"><SourceName>commons</SourceName><TargetName ID="1">commơn</TargetName></Name><Name ID="144"><SourceName>condamine</SourceName><TargetName ID="1">côngđamin</TargetName></Name><Name ID="145"><SourceName>conquistador</SourceName><TargetName ID="1">cônkixờtađo</TargetName></Name><Name ID="146"><SourceName>conring</SourceName><TargetName ID="1">cônrinh</TargetName></Name><Name ID="147"><SourceName>constant</SourceName><TargetName ID="1">conxờtăng</TargetName></Name><Name ID="148"><SourceName>copenhagen</SourceName><TargetName ID="1">côbenhaghen</TargetName></Name><Name ID="149"><SourceName>cornell</SourceName><TargetName ID="1">cônen</TargetName></Name><Name ID="150"><SourceName>correggio</SourceName><TargetName ID="1">côregiô</TargetName></Name><Name ID="151"><SourceName>cottbus</SourceName><TargetName ID="1">cốtbút</TargetName></Name><Name ID="152"><SourceName>cousin</SourceName><TargetName ID="1">cusinh</TargetName></Name><Name ID="153"><SourceName>coventry</SourceName><TargetName ID="1">câuventơry</TargetName></Name><Name ID="154"><SourceName>crick</SourceName><TargetName ID="1">cờrích</TargetName></Name><Name ID="155"><SourceName>cuenca</SourceName><TargetName ID="1">cuenca</TargetName></Name><Name ID="156"><SourceName>curitiba</SourceName><TargetName ID="1">curitiba</TargetName></Name><Name ID="157"><SourceName>ebre</SourceName><TargetName ID="1">ebờrơ</TargetName></Name><Name ID="158"><SourceName>ebro</SourceName><TargetName ID="1">êbờrô</TargetName></Name><Name ID="159"><SourceName>effel</SourceName><TargetName ID="1">épphen</TargetName></Name><Name ID="160"><SourceName>elbasan</SourceName><TargetName ID="1">eobasan</TargetName></Name><Name ID="161"><SourceName>elbe</SourceName><TargetName ID="1">enbơ</TargetName></Name><Name ID="162"><SourceName>ellora</SourceName><TargetName ID="1">elôra</TargetName></Name><Name ID="163"><SourceName>emmanuel</SourceName><TargetName ID="1">emmanuen</TargetName></Name><Name ID="164"><SourceName>encamp</SourceName><TargetName ID="1">encam</TargetName></Name><Name ID="165"><SourceName>enzeli</SourceName><TargetName ID="1">engiêli</TargetName></Name><Name ID="166"><SourceName>erasmus</SourceName><TargetName ID="1">erátmút</TargetName></Name><Name ID="167"><SourceName>ernest</SourceName><TargetName ID="1">écnét</TargetName></Name><Name ID="168"><SourceName>estados</SourceName><TargetName ID="1">éttađốt</TargetName></Name><Name ID="169"><SourceName>estenssoro</SourceName><TargetName ID="1">étsờtensôrô</TargetName></Name><Name ID="170"><SourceName>ettadhamen</SourceName><TargetName ID="1">éttađamen</TargetName></Name><Name ID="171"><SourceName>falkland</SourceName><TargetName ID="1">phôcờlen</TargetName></Name><Name ID="172"><SourceName>fersman</SourceName><TargetName ID="1">phơxờman</TargetName></Name><Name ID="173"><SourceName>fields</SourceName><TargetName ID="1">phiu</TargetName></Name><Name ID="174"><SourceName>filipe</SourceName><TargetName ID="1">philíp</TargetName></Name><Name ID="175"><SourceName>flaminius</SourceName><TargetName ID="1">phờlaminiút</TargetName></Name><Name ID="176"><SourceName>flewelling</SourceName><TargetName ID="1">phờluêlinh</TargetName></Name><Name ID="177"><SourceName>fourier</SourceName><TargetName ID="1">phuriê</TargetName></Name><Name ID="178"><SourceName>fournier</SourceName><TargetName ID="1">phoniơ</TargetName></Name><Name ID="179"><SourceName>freetown</SourceName><TargetName ID="1">phờrithao</TargetName></Name><Name ID="180"><SourceName>frege</SourceName><TargetName ID="1">phờrêgơ</TargetName></Name><Name ID="181"><SourceName>frisian</SourceName><TargetName ID="1">phờrisân</TargetName></Name><Name ID="182"><SourceName>fromaget</SourceName><TargetName ID="1">phờrômagét</TargetName></Name><Name ID="183"><SourceName>fromm</SourceName><TargetName ID="1">phờrom</TargetName></Name><Name ID="184"><SourceName>fundy</SourceName><TargetName ID="1">phânđi</TargetName></Name><Name ID="185"><SourceName>gamow</SourceName><TargetName ID="1">gamốp</TargetName></Name><Name ID="186"><SourceName>garonnes</SourceName><TargetName ID="1">garôn</TargetName></Name><Name ID="187"><SourceName>george</SourceName><TargetName ID="1">giótgiơ</TargetName></Name><Name ID="188"><SourceName>georgij</SourceName><TargetName ID="1">gurơvích</TargetName></Name><Name ID="189"><SourceName>gercen</SourceName><TargetName ID="1">giétxen</TargetName></Name><Name ID="190"><SourceName>gilels</SourceName><TargetName ID="1">ghileo</TargetName></Name><Name ID="191"><SourceName>gilson</SourceName><TargetName ID="1">ghinxơn</TargetName></Name><Name ID="192"><SourceName>giotto</SourceName><TargetName ID="1">giốttô</TargetName></Name><Name ID="193"><SourceName>gitega</SourceName><TargetName ID="1">ghitêga</TargetName></Name><Name ID="194"><SourceName>glazunov</SourceName><TargetName ID="1">gờlagiunốp</TargetName></Name><Name ID="195"><SourceName>godthaab</SourceName><TargetName ID="1">góttháp</TargetName></Name><Name ID="196"><SourceName>golden</SourceName><TargetName ID="1">gônđân</TargetName></Name><Name ID="197"><SourceName>goncourt</SourceName><TargetName ID="1">gôngcua</TargetName></Name><Name ID="198"><SourceName>gorrie</SourceName><TargetName ID="1">gôri</TargetName></Name><Name ID="199"><SourceName>gothic</SourceName><TargetName ID="1">gôtích</TargetName></Name><Name ID="200"><SourceName>graebner</SourceName><TargetName ID="1">gờrépnơ</TargetName></Name><Name ID="201"><SourceName>gram</SourceName><TargetName ID="1">gờram</TargetName></Name><Name ID="202"><SourceName>gregor</SourceName><TargetName ID="1">gờrêgo</TargetName></Name><Name ID="203"><SourceName>grimm</SourceName><TargetName ID="1">gờrim</TargetName></Name><Name ID="204"><SourceName>guggenheim</SourceName><TargetName ID="1">guganham</TargetName></Name><Name ID="205"><SourceName>guyana</SourceName><TargetName ID="1">gudana</TargetName></Name><Name ID="206"><SourceName>hanau</SourceName><TargetName ID="1">hanao</TargetName></Name><Name ID="207"><SourceName>hans</SourceName><TargetName ID="1">han</TargetName></Name><Name ID="208"><SourceName>hardy</SourceName><TargetName ID="1">hađi</TargetName></Name><Name ID="209"><SourceName>harkness</SourceName><TargetName ID="1">hácnét</TargetName></Name><Name ID="210"><SourceName>harunobu</SourceName><TargetName ID="1">harunôbu</TargetName></Name><Name ID="211"><SourceName>haryane</SourceName><TargetName ID="1">harian</TargetName></Name><Name ID="212"><SourceName>hassan</SourceName><TargetName ID="1">hátsan</TargetName></Name><Name ID="213"><SourceName>haussmann</SourceName><TargetName ID="1">hốtman</TargetName></Name><Name ID="214"><SourceName>havel</SourceName><TargetName ID="1">haven</TargetName></Name><Name ID="215"><SourceName>hayam</SourceName><TargetName ID="1">hadam</TargetName></Name><Name ID="216"><SourceName>haydn</SourceName><TargetName ID="1">hayđơn</TargetName></Name><Name ID="217"><SourceName>herculanum</SourceName><TargetName ID="1">hécculanum</TargetName></Name><Name ID="218"><SourceName>herschel</SourceName><TargetName ID="1">hécsen</TargetName></Name><Name ID="219"><SourceName>hesiodos</SourceName><TargetName ID="1">hêsiôđốt</TargetName></Name><Name ID="220"><SourceName>hirohito</SourceName><TargetName ID="1">hirôhitô</TargetName></Name><Name ID="221"><SourceName>hisinger</SourceName><TargetName ID="1">hixingơ</TargetName></Name><Name ID="222"><SourceName>hoban</SourceName><TargetName ID="1">hơbơn</TargetName></Name><Name ID="223"><SourceName>hokusai</SourceName><TargetName ID="1">hôcuxai</TargetName></Name><Name ID="224"><SourceName>honduras</SourceName><TargetName ID="1">hônđurát</TargetName></Name><Name ID="225"><SourceName>honolulu</SourceName><TargetName ID="1">hônôlulu</TargetName></Name><Name ID="226"><SourceName>honshu</SourceName><TargetName ID="1">hônsu</TargetName></Name><Name ID="227"><SourceName>hooke</SourceName><TargetName ID="1">húc</TargetName></Name><Name ID="228"><SourceName>host</SourceName><TargetName ID="1">hótsờ</TargetName></Name><Name ID="229"><SourceName>hulagu</SourceName><TargetName ID="1">hulagu</TargetName></Name><Name ID="230"><SourceName>hume</SourceName><TargetName ID="1">hium</TargetName></Name><Name ID="231"><SourceName>hydaspes</SourceName><TargetName ID="1">hiđaxờbơ</TargetName></Name><Name ID="232"><SourceName>illinois</SourceName><TargetName ID="1">ilinoi</TargetName></Name><Name ID="233"><SourceName>innocento</SourceName><TargetName ID="1">innôxentô</TargetName></Name><Name ID="234"><SourceName>ipoh</SourceName><TargetName ID="1">ibô</TargetName></Name><Name ID="235"><SourceName>isakovich</SourceName><TargetName ID="1">ixacôvích</TargetName></Name><Name ID="236"><SourceName>ishikotrau</SourceName><TargetName ID="1">isicôtrau</TargetName></Name><Name ID="237"><SourceName>issus</SourceName><TargetName ID="1">ixút</TargetName></Name><Name ID="238"><SourceName>jacob</SourceName><TargetName ID="1">giacốp</TargetName></Name><Name ID="239"><SourceName>jima</SourceName><TargetName ID="1">gima</TargetName></Name><Name ID="240"><SourceName>joyce</SourceName><TargetName ID="1">gioixơ</TargetName></Name><Name ID="241"><SourceName>kaifeng</SourceName><TargetName ID="1">khaipheng</TargetName></Name><Name ID="242"><SourceName>kamba</SourceName><TargetName ID="1">camba</TargetName></Name><Name ID="243"><SourceName>kampot</SourceName><TargetName ID="1">cămbốt</TargetName></Name><Name ID="244"><SourceName>kanchanaburi</SourceName><TargetName ID="1">canchanaburi</TargetName></Name><Name ID="245"><SourceName>kandy</SourceName><TargetName ID="1">canđi</TargetName></Name><Name ID="246"><SourceName>karasu</SourceName><TargetName ID="1">carasu</TargetName></Name><Name ID="247"><SourceName>karpov</SourceName><TargetName ID="1">cácbốp</TargetName></Name><Name ID="248"><SourceName>karsk</SourceName><TargetName ID="1">cácxờcơ</TargetName></Name><Name ID="249"><SourceName>kartli</SourceName><TargetName ID="1">cácli</TargetName></Name><Name ID="250"><SourceName>kashmir</SourceName><TargetName ID="1">cátsờmia</TargetName></Name><Name ID="251"><SourceName>kaspi</SourceName><TargetName ID="1">cátsờbi</TargetName></Name><Name ID="252"><SourceName>kaunas</SourceName><TargetName ID="1">caunát</TargetName></Name><Name ID="253"><SourceName>kazanskij</SourceName><TargetName ID="1">kagianxờki</TargetName></Name><Name ID="254"><SourceName>keio</SourceName><TargetName ID="1">keo</TargetName></Name><Name ID="255"><SourceName>kellogg</SourceName><TargetName ID="1">kêlốc</TargetName></Name><Name ID="256"><SourceName>kendrew</SourceName><TargetName ID="1">kenđờriu</TargetName></Name><Name ID="257"><SourceName>kentucky</SourceName><TargetName ID="1">kentúcki</TargetName></Name><Name ID="258"><SourceName>kenya</SourceName><TargetName ID="1">kênia</TargetName></Name><Name ID="259"><SourceName>ketterle</SourceName><TargetName ID="1">kêtơlơ</TargetName></Name><Name ID="260"><SourceName>khabarovsk</SourceName><TargetName ID="1">khabarốpxờki</TargetName></Name><Name ID="261"><SourceName>khariton</SourceName><TargetName ID="1">kharitôn</TargetName></Name><Name ID="262"><SourceName>kilauea</SourceName><TargetName ID="1">kilaua</TargetName></Name><Name ID="263"><SourceName>kiribati</SourceName><TargetName ID="1">kiribati</TargetName></Name><Name ID="264"><SourceName>kirov</SourceName><TargetName ID="1">kirốp</TargetName></Name><Name ID="265"><SourceName>kismaayo</SourceName><TargetName ID="1">kixờmayô</TargetName></Name><Name ID="266"><SourceName>kitaj</SourceName><TargetName ID="1">kitai</TargetName></Name><Name ID="267"><SourceName>kjeldahl</SourceName><TargetName ID="1">kiênđan</TargetName></Name><Name ID="268"><SourceName>koechlin</SourceName><TargetName ID="1">côétlin</TargetName></Name><Name ID="269"><SourceName>kolonia</SourceName><TargetName ID="1">côlônia</TargetName></Name><Name ID="270"><SourceName>komer</SourceName><TargetName ID="1">cômơ</TargetName></Name><Name ID="271"><SourceName>koudougou</SourceName><TargetName ID="1">cuđugu</TargetName></Name><Name ID="272"><SourceName>kragujevac</SourceName><TargetName ID="1">cờraguiêvắc</TargetName></Name><Name ID="273"><SourceName>krasnodar</SourceName><TargetName ID="1">cờrátnôđa</TargetName></Name><Name ID="274"><SourceName>kromdraai</SourceName><TargetName ID="1">cờrômđờrai</TargetName></Name><Name ID="275"><SourceName>kunstkammer</SourceName><TargetName ID="1">cunsờtơcamơ</TargetName></Name><Name ID="276"><SourceName>kuznecov</SourceName><TargetName ID="1">cugiơnétxốp</TargetName></Name><Name ID="277"><SourceName>lachaise</SourceName><TargetName ID="1">lachai</TargetName></Name><Name ID="278"><SourceName>laforgue</SourceName><TargetName ID="1">laphótghiu</TargetName></Name><Name ID="279"><SourceName>lagny</SourceName><TargetName ID="1">lanhy</TargetName></Name><Name ID="280"><SourceName>lamarck</SourceName><TargetName ID="1">lamắc</TargetName></Name><Name ID="281"><SourceName>lancelot</SourceName><TargetName ID="1">lăngxơlô</TargetName></Name><Name ID="282"><SourceName>lane</SourceName><TargetName ID="1">len</TargetName></Name><Name ID="283"><SourceName>laperuza</SourceName><TargetName ID="1">laberugia</TargetName></Name><Name ID="284"><SourceName>lask</SourceName><TargetName ID="1">látsờcơ</TargetName></Name><Name ID="285"><SourceName>latour</SourceName><TargetName ID="1">latua</TargetName></Name><Name ID="286"><SourceName>laughlin</SourceName><TargetName ID="1">láplin</TargetName></Name><Name ID="287"><SourceName>leone</SourceName><TargetName ID="1">lêôn</TargetName></Name><Name ID="288"><SourceName>leonid</SourceName><TargetName ID="1">lêônít</TargetName></Name><Name ID="289"><SourceName>leontief</SourceName><TargetName ID="1">lêôntiép</TargetName></Name><Name ID="290"><SourceName>lermontov</SourceName><TargetName ID="1">lécmôntốp</TargetName></Name><Name ID="291"><SourceName>lerne</SourceName><TargetName ID="1">lơn</TargetName></Name><Name ID="292"><SourceName>lesbos</SourceName><TargetName ID="1">lêsờbô</TargetName></Name><Name ID="293"><SourceName>lescot</SourceName><TargetName ID="1">létxờcót</TargetName></Name><Name ID="294"><SourceName>leucippe</SourceName><TargetName ID="1">lơxíp</TargetName></Name><Name ID="295"><SourceName>lhote</SourceName><TargetName ID="1">lốt</TargetName></Name><Name ID="296"><SourceName>libby</SourceName><TargetName ID="1">libi</TargetName></Name><Name ID="297"><SourceName>liebknecht</SourceName><TargetName ID="1">liếpnếch</TargetName></Name><Name ID="298"><SourceName>lietuvos</SourceName><TargetName ID="1">lítva</TargetName></Name><Name ID="299"><SourceName>limmat</SourceName><TargetName ID="1">limát</TargetName></Name><Name ID="300"><SourceName>little</SourceName><TargetName ID="1">líttô</TargetName></Name><Name ID="301"><SourceName>loango</SourceName><TargetName ID="1">lôănggô</TargetName></Name><Name ID="302"><SourceName>lobito</SourceName><TargetName ID="1">lôbitu</TargetName></Name><Name ID="303"><SourceName>lualaba</SourceName><TargetName ID="1">lualaba</TargetName></Name><Name ID="304"><SourceName>lucien</SourceName><TargetName ID="1">luxiân</TargetName></Name><Name ID="305"><SourceName>luckenwalde</SourceName><TargetName ID="1">lúckenvanđơ</TargetName></Name><Name ID="306"><SourceName>lully</SourceName><TargetName ID="1">luyly</TargetName></Name><Name ID="307"><SourceName>lusitani</SourceName><TargetName ID="1">luditani</TargetName></Name><Name ID="308"><SourceName>luther</SourceName><TargetName ID="1">luthơ</TargetName></Name><Name ID="309"><SourceName>lwoff</SourceName><TargetName ID="1">lơvốp</TargetName></Name><Name ID="310"><SourceName>lykeios</SourceName><TargetName ID="1">licâyốt</TargetName></Name><Name ID="311"><SourceName>maastricht</SourceName><TargetName ID="1">mátsờtrích</TargetName></Name><Name ID="312"><SourceName>mably</SourceName><TargetName ID="1">mabờli</TargetName></Name><Name ID="313"><SourceName>maccarthy</SourceName><TargetName ID="1">máccathy</TargetName></Name><Name ID="314"><SourceName>madagascar</SourceName><TargetName ID="1">mađagátsờca</TargetName></Name><Name ID="315"><SourceName>magdalena</SourceName><TargetName ID="1">mácđalêna</TargetName></Name><Name ID="316"><SourceName>mahall</SourceName><TargetName ID="1">mahan</TargetName></Name><Name ID="317"><SourceName>mahler</SourceName><TargetName ID="1">malơ</TargetName></Name><Name ID="318"><SourceName>maillol</SourceName><TargetName ID="1">mailon</TargetName></Name><Name ID="319"><SourceName>makarova</SourceName><TargetName ID="1">macarôva</TargetName></Name><Name ID="320"><SourceName>makino</SourceName><TargetName ID="1">makinô</TargetName></Name><Name ID="321"><SourceName>malevich</SourceName><TargetName ID="1">malêvích</TargetName></Name><Name ID="322"><SourceName>manaut</SourceName><TargetName ID="1">manau</TargetName></Name><Name ID="323"><SourceName>manet</SourceName><TargetName ID="1">manét</TargetName></Name><Name ID="324"><SourceName>mar</SourceName><TargetName ID="1">marờ</TargetName></Name><Name ID="325"><SourceName>marchais</SourceName><TargetName ID="1">mácse</TargetName></Name><Name ID="326"><SourceName>marconi</SourceName><TargetName ID="1">máccôni</TargetName></Name><Name ID="327"><SourceName>marinetti</SourceName><TargetName ID="1">marinétti</TargetName></Name><Name ID="328"><SourceName>marino</SourceName><TargetName ID="1">marinô</TargetName></Name><Name ID="329"><SourceName>mariotte</SourceName><TargetName ID="1">mariốt</TargetName></Name><Name ID="330"><SourceName>maritain</SourceName><TargetName ID="1">maritan</TargetName></Name><Name ID="331"><SourceName>markovo</SourceName><TargetName ID="1">máccôvô</TargetName></Name><Name ID="332"><SourceName>martinson</SourceName><TargetName ID="1">máctinxơn</TargetName></Name><Name ID="333"><SourceName>mashhad</SourceName><TargetName ID="1">mátsờhát</TargetName></Name><Name ID="334"><SourceName>mashonaland</SourceName><TargetName ID="1">masônalen</TargetName></Name><Name ID="335"><SourceName>masina</SourceName><TargetName ID="1">masina</TargetName></Name><Name ID="336"><SourceName>masown</SourceName><TargetName ID="1">maxơn</TargetName></Name><Name ID="337"><SourceName>massine</SourceName><TargetName ID="1">masin</TargetName></Name><Name ID="338"><SourceName>mathieu</SourceName><TargetName ID="1">mathiơ</TargetName></Name><Name ID="339"><SourceName>mato</SourceName><TargetName ID="1">matu</TargetName></Name><Name ID="340"><SourceName>matta</SourceName><TargetName ID="1">mátta</TargetName></Name><Name ID="341"><SourceName>maudao</SourceName><TargetName ID="1">mauđao</TargetName></Name><Name ID="342"><SourceName>mavaca</SourceName><TargetName ID="1">mavaca</TargetName></Name><Name ID="343"><SourceName>mboshi</SourceName><TargetName ID="1">mơbôsi</TargetName></Name><Name ID="344"><SourceName>mckinley</SourceName><TargetName ID="1">máckinli</TargetName></Name><Name ID="345"><SourceName>meckel</SourceName><TargetName ID="1">méchken</TargetName></Name><Name ID="346"><SourceName>medan</SourceName><TargetName ID="1">mêđan</TargetName></Name><Name ID="347"><SourceName>medvednica</SourceName><TargetName ID="1">métvétnica</TargetName></Name><Name ID="348"><SourceName>mehring</SourceName><TargetName ID="1">mêrinh</TargetName></Name><Name ID="349"><SourceName>meillet</SourceName><TargetName ID="1">mâylét</TargetName></Name><Name ID="350"><SourceName>mendelsohn</SourceName><TargetName ID="1">menđenxơn</TargetName></Name><Name ID="351"><SourceName>mesurado</SourceName><TargetName ID="1">mêxurađô</TargetName></Name><Name ID="352"><SourceName>metagenes</SourceName><TargetName ID="1">mêtaghênét</TargetName></Name><Name ID="353"><SourceName>michoacan</SourceName><TargetName ID="1">michôacan</TargetName></Name><Name ID="354"><SourceName>mickiewicz</SourceName><TargetName ID="1">mítkiêvích</TargetName></Name><Name ID="355"><SourceName>miguelito</SourceName><TargetName ID="1">mighêlitô</TargetName></Name><Name ID="356"><SourceName>milankovich</SourceName><TargetName ID="1">milancôvít</TargetName></Name><Name ID="357"><SourceName>mincus</SourceName><TargetName ID="1">mincút</TargetName></Name><Name ID="358"><SourceName>minin</SourceName><TargetName ID="1">minin</TargetName></Name><Name ID="359"><SourceName>minos</SourceName><TargetName ID="1">minốt</TargetName></Name><Name ID="360"><SourceName>moholy</SourceName><TargetName ID="1">môhôly</TargetName></Name><Name ID="361"><SourceName>mongo</SourceName><TargetName ID="1">môngô</TargetName></Name><Name ID="362"><SourceName>montesquieu</SourceName><TargetName ID="1">môngtétkiơ</TargetName></Name><Name ID="363"><SourceName>montmorillon</SourceName><TargetName ID="1">mônmôrilon</TargetName></Name><Name ID="364"><SourceName>morisot</SourceName><TargetName ID="1">môrigiô</TargetName></Name><Name ID="365"><SourceName>moskva</SourceName><TargetName ID="1">mátxờcơva</TargetName></Name><Name ID="366"><SourceName>mounier</SourceName><TargetName ID="1">muniê</TargetName></Name><Name ID="367"><SourceName>moustier</SourceName><TargetName ID="1">maosờtiơ</TargetName></Name><Name ID="368"><SourceName>muhammad</SourceName><TargetName ID="1">muhamét</TargetName></Name><Name ID="369"><SourceName>mukden</SourceName><TargetName ID="1">múcđen</TargetName></Name><Name ID="370"><SourceName>mullerup</SourceName><TargetName ID="1">mulerúp</TargetName></Name><Name ID="371"><SourceName>munku</SourceName><TargetName ID="1">muncu</TargetName></Name><Name ID="372"><SourceName>murmansk</SourceName><TargetName ID="1">muamansờcơ</TargetName></Name><Name ID="373"><SourceName>mutare</SourceName><TargetName ID="1">mutarê</TargetName></Name><Name ID="374"><SourceName>mymensingh</SourceName><TargetName ID="1">mymenxingơ</TargetName></Name><Name ID="375"><SourceName>nagel</SourceName><TargetName ID="1">naghen</TargetName></Name><Name ID="376"><SourceName>namangan</SourceName><TargetName ID="1">namangan</TargetName></Name><Name ID="377"><SourceName>narva</SourceName><TargetName ID="1">nácva</TargetName></Name><Name ID="378"><SourceName>natorp</SourceName><TargetName ID="1">natócbơ</TargetName></Name><Name ID="379"><SourceName>navarre</SourceName><TargetName ID="1">nava</TargetName></Name><Name ID="380"><SourceName>negros</SourceName><TargetName ID="1">nêgờrốt</TargetName></Name><Name ID="381"><SourceName>neimeng</SourceName><TargetName ID="1">nâymeng</TargetName></Name><Name ID="382"><SourceName>nelson</SourceName><TargetName ID="1">nenxơn</TargetName></Name><Name ID="383"><SourceName>nervi</SourceName><TargetName ID="1">nécvi</TargetName></Name><Name ID="384"><SourceName>neseby</SourceName><TargetName ID="1">nétsờbai</TargetName></Name><Name ID="385"><SourceName>nikolaevsk</SourceName><TargetName ID="1">nicôlaépxờcơ</TargetName></Name><Name ID="386"><SourceName>ninigi</SourceName><TargetName ID="1">ninigi</TargetName></Name><Name ID="387"><SourceName>nkomo</SourceName><TargetName ID="1">nơcômô</TargetName></Name><Name ID="388"><SourceName>nolde</SourceName><TargetName ID="1">nônđơ</TargetName></Name><Name ID="389"><SourceName>novi</SourceName><TargetName ID="1">nôvi</TargetName></Name><Name ID="390"><SourceName>novosibirsk</SourceName><TargetName ID="1">nôvôsibiasờcơ</TargetName></Name><Name ID="391"><SourceName>nukualofa</SourceName><TargetName ID="1">nukualôpha</TargetName></Name><Name ID="392"><SourceName>octavius</SourceName><TargetName ID="1">óctaviút</TargetName></Name><Name ID="393"><SourceName>pak</SourceName><TargetName ID="1">bắc</TargetName></Name><Name ID="394"><SourceName>pane</SourceName><TargetName ID="1">banê</TargetName></Name><Name ID="395"><SourceName>paolo</SourceName><TargetName ID="1">baolô</TargetName></Name><Name ID="396"><SourceName>paraguay</SourceName><TargetName ID="1">baraquay</TargetName></Name><Name ID="397"><SourceName>parma</SourceName><TargetName ID="1">bácma</TargetName></Name><Name ID="398"><SourceName>parsons</SourceName><TargetName ID="1">basân</TargetName></Name><Name ID="399"><SourceName>patesi</SourceName><TargetName ID="1">patêxi</TargetName></Name><Name ID="400"><SourceName>paulus</SourceName><TargetName ID="1">baolút</TargetName></Name><Name ID="401"><SourceName>pavlovsk</SourceName><TargetName ID="1">báplốpsờcơ</TargetName></Name><Name ID="402"><SourceName>paxton</SourceName><TargetName ID="1">bắcxờtơn</TargetName></Name><Name ID="403"><SourceName>peggy</SourceName><TargetName ID="1">bêghi</TargetName></Name><Name ID="404"><SourceName>pegu</SourceName><TargetName ID="1">bêgu</TargetName></Name><Name ID="405"><SourceName>pelman</SourceName><TargetName ID="1">benman</TargetName></Name><Name ID="406"><SourceName>penzias</SourceName><TargetName ID="1">bengiát</TargetName></Name><Name ID="407"><SourceName>perov</SourceName><TargetName ID="1">bêrốp</TargetName></Name><Name ID="408"><SourceName>phong</SourceName><TargetName ID="1">phong</TargetName></Name><Name ID="409"><SourceName>piccard</SourceName><TargetName ID="1">bica</TargetName></Name><Name ID="410"><SourceName>plekhanov</SourceName><TargetName ID="1">phờlêkhanốp</TargetName></Name><Name ID="411"><SourceName>ploutarkhos</SourceName><TargetName ID="1">phờlautakhơ</TargetName></Name><Name ID="412"><SourceName>polonnaruwa</SourceName><TargetName ID="1">bôlônnaruva</TargetName></Name><Name ID="413"><SourceName>polybe</SourceName><TargetName ID="1">pôlubiốt</TargetName></Name><Name ID="414"><SourceName>pontrjagin</SourceName><TargetName ID="1">bôntriaghin</TargetName></Name><Name ID="415"><SourceName>preto</SourceName><TargetName ID="1">phờrêtu</TargetName></Name><Name ID="416"><SourceName>prior</SourceName><TargetName ID="1">phờraiơ</TargetName></Name><Name ID="417"><SourceName>pylos</SourceName><TargetName ID="1">bilốt</TargetName></Name><Name ID="418"><SourceName>pythyos</SourceName><TargetName ID="1">bitiốt</TargetName></Name><Name ID="419"><SourceName>rabelais</SourceName><TargetName ID="1">rabilây</TargetName></Name><Name ID="420"><SourceName>rance</SourceName><TargetName ID="1">răngxơ</TargetName></Name><Name ID="421"><SourceName>ras</SourceName><TargetName ID="1">rát</TargetName></Name><Name ID="422"><SourceName>ravi</SourceName><TargetName ID="1">ravi</TargetName></Name><Name ID="423"><SourceName>ray</SourceName><TargetName ID="1">rây</TargetName></Name><Name ID="424"><SourceName>rebreanu</SourceName><TargetName ID="1">rêbờrêanu</TargetName></Name><Name ID="425"><SourceName>riemann</SourceName><TargetName ID="1">riman</TargetName></Name><Name ID="426"><SourceName>rimbaud</SourceName><TargetName ID="1">rimbao</TargetName></Name><Name ID="427"><SourceName>robinet</SourceName><TargetName ID="1">rôbinét</TargetName></Name><Name ID="428"><SourceName>roggeveen</SourceName><TargetName ID="1">rôghêven</TargetName></Name><Name ID="429"><SourceName>roken</SourceName><TargetName ID="1">rôken</TargetName></Name><Name ID="430"><SourceName>rorschach</SourceName><TargetName ID="1">rôsắc</TargetName></Name><Name ID="431"><SourceName>rose</SourceName><TargetName ID="1">rôdơ</TargetName></Name><Name ID="432"><SourceName>rosenbusch</SourceName><TargetName ID="1">rôsenbusơ</TargetName></Name><Name ID="433"><SourceName>rouault</SourceName><TargetName ID="1">raoốt</TargetName></Name><Name ID="434"><SourceName>roux</SourceName><TargetName ID="1">ru</TargetName></Name><Name ID="435"><SourceName>ruhengeri</SourceName><TargetName ID="1">ruhenghêri</TargetName></Name><Name ID="436"><SourceName>rutland</SourceName><TargetName ID="1">rútlen</TargetName></Name><Name ID="437"><SourceName>ruysdael</SourceName><TargetName ID="1">ruysờđaên</TargetName></Name><Name ID="438"><SourceName>samurai</SourceName><TargetName ID="1">samurai</TargetName></Name><Name ID="439"><SourceName>schmoller</SourceName><TargetName ID="1">sờmônlơ</TargetName></Name><Name ID="440"><SourceName>schwarzschild</SourceName><TargetName ID="1">sờquasờchaiô</TargetName></Name><Name ID="441"><SourceName>sharp</SourceName><TargetName ID="1">sáp</TargetName></Name><Name ID="442"><SourceName>shelley</SourceName><TargetName ID="1">seli</TargetName></Name><Name ID="443"><SourceName>sheridan</SourceName><TargetName ID="1">seriđân</TargetName></Name><Name ID="444"><SourceName>shetland</SourceName><TargetName ID="1">sétlen</TargetName></Name><Name ID="445"><SourceName>shilka</SourceName><TargetName ID="1">sinca</TargetName></Name><Name ID="446"><SourceName>sholokhov</SourceName><TargetName ID="1">sôlôkhốp</TargetName></Name><Name ID="447"><SourceName>shukshin</SourceName><TargetName ID="1">sắcsan</TargetName></Name><Name ID="448"><SourceName>steiner</SourceName><TargetName ID="1">sờtainơ</TargetName></Name><Name ID="449"><SourceName>tabor</SourceName><TargetName ID="1">taborờ</TargetName></Name><Name ID="450"><SourceName>tagpochau</SourceName><TargetName ID="1">tabôchau</TargetName></Name><Name ID="451"><SourceName>talet</SourceName><TargetName ID="1">talét</TargetName></Name><Name ID="452"><SourceName>tamara</SourceName><TargetName ID="1">tamara</TargetName></Name><Name ID="453"><SourceName>tana</SourceName><TargetName ID="1">tana</TargetName></Name><Name ID="454"><SourceName>tanizaki</SourceName><TargetName ID="1">tanigiaki</TargetName></Name><Name ID="455"><SourceName>taranto</SourceName><TargetName ID="1">tarantô</TargetName></Name><Name ID="456"><SourceName>taukum</SourceName><TargetName ID="1">taucum</TargetName></Name><Name ID="457"><SourceName>thar</SourceName><TargetName ID="1">tha</TargetName></Name><Name ID="458"><SourceName>thenard</SourceName><TargetName ID="1">têna</TargetName></Name><Name ID="459"><SourceName>tibre</SourceName><TargetName ID="1">tibờrơ</TargetName></Name><Name ID="460"><SourceName>tiffeneau</SourceName><TargetName ID="1">tiphanô</TargetName></Name><Name ID="461"><SourceName>timmermans</SourceName><TargetName ID="1">timmécman</TargetName></Name><Name ID="462"><SourceName>timor</SourceName><TargetName ID="1">timo</TargetName></Name><Name ID="463"><SourceName>tinbergen</SourceName><TargetName ID="1">tinbécghen</TargetName></Name><Name ID="464"><SourceName>tirreno</SourceName><TargetName ID="1">tirênô</TargetName></Name><Name ID="465"><SourceName>titien</SourceName><TargetName ID="1">titiên</TargetName></Name><Name ID="466"><SourceName>tokunnaga</SourceName><TargetName ID="1">tôcunnaga</TargetName></Name><Name ID="467"><SourceName>tongatapu</SourceName><TargetName ID="1">tôngatabu</TargetName></Name><Name ID="468"><SourceName>toronto</SourceName><TargetName ID="1">tôrontô</TargetName></Name><Name ID="469"><SourceName>torricelli</SourceName><TargetName ID="1">tôricheli</TargetName></Name><Name ID="470"><SourceName>toulon</SourceName><TargetName ID="1">tulông</TargetName></Name><Name ID="471"><SourceName>trondheim</SourceName><TargetName ID="1">trônhem</TargetName></Name><Name ID="472"><SourceName>tropinin</SourceName><TargetName ID="1">tơrôbinin</TargetName></Name><Name ID="473"><SourceName>truchsess</SourceName><TargetName ID="1">trusét</TargetName></Name><Name ID="474"><SourceName>truffaut</SourceName><TargetName ID="1">truyphô</TargetName></Name><Name ID="475"><SourceName>truman</SourceName><TargetName ID="1">tơruman</TargetName></Name><Name ID="476"><SourceName>tunguska</SourceName><TargetName ID="1">tunguxờca</TargetName></Name><Name ID="477"><SourceName>turgenev</SourceName><TargetName ID="1">tuốcghênép</TargetName></Name><Name ID="478"><SourceName>twain</SourceName><TargetName ID="1">tuên</TargetName></Name><Name ID="479"><SourceName>uelen</SourceName><TargetName ID="1">uêlen</TargetName></Name><Name ID="480"><SourceName>utta</SourceName><TargetName ID="1">útta</TargetName></Name><Name ID="481"><SourceName>valencia</SourceName><TargetName ID="1">valenxia</TargetName></Name><Name ID="482"><SourceName>valens</SourceName><TargetName ID="1">valen</TargetName></Name><Name ID="483"><SourceName>varna</SourceName><TargetName ID="1">vácna</TargetName></Name><Name ID="484"><SourceName>vauban</SourceName><TargetName ID="1">vôbăng</TargetName></Name><Name ID="485"><SourceName>verdi</SourceName><TargetName ID="1">vécđi</TargetName></Name><Name ID="486"><SourceName>verga</SourceName><TargetName ID="1">vécga</TargetName></Name><Name ID="487"><SourceName>vergilius</SourceName><TargetName ID="1">vécgiliút</TargetName></Name><Name ID="488"><SourceName>vilhelm</SourceName><TargetName ID="1">vinhem</TargetName></Name><Name ID="489"><SourceName>virgile</SourceName><TargetName ID="1">viếcgin</TargetName></Name><Name ID="490"><SourceName>vodkin</SourceName><TargetName ID="1">vốtkin</TargetName></Name><Name ID="491"><SourceName>voznesenskij</SourceName><TargetName ID="1">vôgiờnêsenxờki</TargetName></Name><Name ID="492"><SourceName>xieng</SourceName><TargetName ID="1">xiêng</TargetName></Name><Name ID="493"><SourceName>yale</SourceName><TargetName ID="1">den</TargetName></Name><Name ID="494"><SourceName>yamazaki</SourceName><TargetName ID="1">damagiaki</TargetName></Name><Name ID="495"><SourceName>yamoussoukro</SourceName><TargetName ID="1">damaosờcờrô</TargetName></Name><Name ID="496"><SourceName>yatenga</SourceName><TargetName ID="1">datenga</TargetName></Name><Name ID="497"><SourceName>zahir</SourceName><TargetName ID="1">giahia</TargetName></Name><Name ID="498"><SourceName>zakopane</SourceName><TargetName ID="1">giacôben</TargetName></Name><Name ID="499"><SourceName>zavojskij</SourceName><TargetName ID="1">giavoisờki</TargetName></Name><Name ID="500"><SourceName>zeravshan</SourceName><TargetName ID="1">giêrápsan</TargetName></Name></TransliterationCorpus>